sugarrush/__init__.py
sugarrush/solver.py
sugarrush/utils.py
sugarrush/examples/disjunction.py
sugarrush/examples/langford.py
sugarrush/examples/parity_board.py
sugarrush/examples/pincus.py
sugarrush/examples/tests.py
sugarrush-0.0.5.dist-info/LICENSE
sugarrush-0.0.5.dist-info/METADATA
sugarrush-0.0.5.dist-info/WHEEL
sugarrush-0.0.5.dist-info/top_level.txt
sugarrush-0.0.5.dist-info/RECORD
