Metadata-Version: 2.1
Name: sugarrush
Version: 0.0.5
Summary: Quality-of-life and extra features for python-sat
Home-page: https://github.com/jonatanwestholm/sugarrush
Author: Jonatan Westholm
Author-email: jonatanwestholm@gmail.com
License: UNKNOWN
Platform: UNKNOWN
Classifier: Programming Language :: Python :: 3
Classifier: License :: OSI Approved :: MIT License
Classifier: Operating System :: OS Independent
Requires-Python: >=3.6
